{
 "version": "1.0",
 "dataVerified": "2026-06-11",
 "source": "fedasil.be/en/reception-centres (liste officielle, consultée le 11/06/2026 — inclut les reprises Fedasil de janvier 2026)",
 "note": {
  "fr": "Tous les centres d'accueil officiels du réseau Fedasil (fédéraux + partenaires Croix-Rouge/Rode Kruis/autres). Les COO (Steenokkerzeel, Sugny, Oudergem) sont les centres d'observation et d'orientation par lesquels passent les MENA à l'arrivée ; la plupart des grands centres ont une aile MENA — confirmez auprès du dispatching Fedasil. Pour les ILA/LOI (places CPAS) et la semi-autonomie : pas d'annuaire centralisé public, contactez le CPAS de la commune ou le référent Fedasil du jeune.",
  "nl": "Alle officiële opvangcentra van het Fedasil-netwerk (federaal + partners Rode Kruis/Croix-Rouge/andere). De OOC's (Steenokkerzeel, Sugny, Oudergem) zijn de observatie- en oriëntatiecentra voor NBMV bij aankomst; de meeste grote centra hebben een NBMV-vleugel — bevestig bij de Fedasil-dispatching. Voor LOI's (OCMW-plaatsen) en begeleid zelfstandig wonen: geen centrale publieke gids, contacteer het OCMW van de gemeente of de Fedasil-referent."
 },
 "types": {
  "coo": {
   "fr": "Centre d'observation et d'orientation (arrivée MENA)",
   "nl": "Observatie- en oriëntatiecentrum (aankomst NBMV)"
  },
  "mena": {
   "fr": "Centre spécifique MENA",
   "nl": "Specifiek NBMV-centrum"
  },
  "collectif": {
   "fr": "Centre d'accueil collectif (souvent avec aile MENA)",
   "nl": "Collectief opvangcentrum (vaak met NBMV-vleugel)"
  },
  "ila": {
   "fr": "ILA/LOI — place CPAS (via le CPAS communal)",
   "nl": "LOI — OCMW-plaats (via het gemeentelijk OCMW)"
  },
  "semi": {
   "fr": "Semi-autonomie / logement supervisé (via Fedasil/CPAS)",
   "nl": "Begeleid zelfstandig wonen (via Fedasil/OCMW)"
  }
 },
 "centres": [
  {
   "nom": "Jalhay",
   "operateur": "fedasil",
   "operateurLbl": "Fedasil",
   "type": "collectif",
   "region": "WAL",
   "rue": "Stockay 17",
   "cp": "4845",
   "commune": "Jalhay",
   "adresse": "Stockay 17, 4845 Jalhay"
  },
  {
   "nom": "Marcinelle",
   "operateur": "fedasil",
   "operateurLbl": "Fedasil",
   "type": "collectif",
   "region": "WAL",
   "rue": "Rue Cité de l'Enfance 45",
   "cp": "6001",
   "commune": "Marcinelle",
   "adresse": "Rue Cité de l'Enfance 45, 6001 Marcinelle"
  },
  {
   "nom": "Schilde",
   "operateur": "fedasil",
   "operateurLbl": "Fedasil",
   "type": "collectif",
   "region": "VLA",
   "rue": "Brasschaatsebaan 126",
   "cp": "2970",
   "commune": "Schilde",
   "adresse": "Brasschaatsebaan 126, 2970 Schilde"
  },
  {
   "nom": "Gent Muink",
   "operateur": "fedasil",
   "operateurLbl": "Fedasil",
   "type": "collectif",
   "region": "VLA",
   "rue": "Hofstraat 47",
   "cp": "9000",
   "commune": "Gent",
   "adresse": "Hofstraat 47, 9000 Gent"
  },
  {
   "nom": "Braine-le-Comte",
   "operateur": "fedasil",
   "operateurLbl": "Fedasil",
   "type": "collectif",
   "region": "WAL",
   "rue": "Rue Père Damien 16",
   "cp": "7090",
   "commune": "Braine-le-Comte",
   "adresse": "Rue Père Damien 16, 7090 Braine-le-Comte"
  },
  {
   "nom": "Grimbergen",
   "operateur": "fedasil",
   "operateurLbl": "Fedasil",
   "type": "collectif",
   "region": "VLA",
   "rue": "Bergdal 16",
   "cp": "1853",
   "commune": "Grimbergen",
   "adresse": "Bergdal 16, 1853 Grimbergen"
  },
  {
   "nom": "Alveringem",
   "operateur": "fedasil",
   "operateurLbl": "Fedasil",
   "type": "collectif",
   "region": "VLA",
   "rue": "Gapaard 9",
   "cp": "8690",
   "commune": "Alveringem",
   "adresse": "Gapaard 9, 8690 Alveringem"
  },
  {
   "nom": "Morlanwelz",
   "operateur": "fedasil",
   "operateurLbl": "Fedasil",
   "type": "collectif",
   "region": "WAL",
   "rue": "Chaussée de Mariemont 92",
   "cp": "7140",
   "commune": "Morlanwelz",
   "adresse": "Chaussée de Mariemont 92, 7140 Morlanwelz"
  },
  {
   "nom": "Walcourt",
   "operateur": "fedasil",
   "operateurLbl": "Fedasil",
   "type": "collectif",
   "region": "WAL",
   "rue": "Rue Toffette 16",
   "cp": "5650",
   "commune": "Walcourt",
   "adresse": "Rue Toffette 16, 5650 Walcourt"
  },
  {
   "nom": "Schaerbeek",
   "operateur": "fedasil",
   "operateurLbl": "Fedasil",
   "type": "collectif",
   "region": "BXL",
   "rue": "Boulevard Lambermont 322",
   "cp": "1030",
   "commune": "Schaerbeek",
   "adresse": "Boulevard Lambermont 322, 1030 Schaerbeek"
  },
  {
   "nom": "Bruxelles Bordet",
   "operateur": "fedasil",
   "operateurLbl": "Fedasil",
   "type": "collectif",
   "region": "BXL",
   "rue": "Rue aux Laines 200",
   "cp": "1000",
   "commune": "Bruxelles",
   "adresse": "Rue aux Laines 200, 1000 Bruxelles"
  },
  {
   "nom": "Spa",
   "operateur": "fedasil",
   "operateurLbl": "Fedasil",
   "type": "collectif",
   "region": "WAL",
   "rue": "Spaloumont 5",
   "cp": "4900",
   "commune": "Spa",
   "adresse": "Spaloumont 5, 4900 Spa"
  },
  {
   "nom": "Machelen",
   "operateur": "fedasil",
   "operateurLbl": "Fedasil",
   "type": "collectif",
   "region": "VLA",
   "rue": "Bessenveldstraat 15",
   "cp": "1831",
   "commune": "Machelen",
   "adresse": "Bessenveldstraat 15, 1831 Machelen"
  },
  {
   "nom": "Sint-Jans-Molenbeek",
   "operateur": "fedasil",
   "operateurLbl": "Fedasil",
   "type": "collectif",
   "region": "BXL",
   "rue": "François Sebrechtslaan 40",
   "cp": "1080",
   "commune": "Sint-Jans-Molenbeek",
   "adresse": "François Sebrechtslaan 40, 1080 Sint-Jans-Molenbeek"
  },
  {
   "nom": "Dilbeek",
   "operateur": "fedasil",
   "operateurLbl": "Fedasil",
   "type": "collectif",
   "region": "VLA",
   "rue": "Kattebroekstraat 199",
   "cp": "1700",
   "commune": "Dilbeek",
   "adresse": "Kattebroekstraat 199, 1700 Dilbeek"
  },
  {
   "nom": "Poelkapelle",
   "operateur": "fedasil",
   "operateurLbl": "Fedasil",
   "type": "collectif",
   "region": "VLA",
   "rue": "Stadensteenweg 68",
   "cp": "8920",
   "commune": "Poelkapelle",
   "adresse": "Stadensteenweg 68, 8920 Poelkapelle"
  },
  {
   "nom": "Glons",
   "operateur": "fedasil",
   "operateurLbl": "Fedasil",
   "type": "collectif",
   "region": "WAL",
   "rue": "Thier Mathias 1B",
   "cp": "4690",
   "commune": "Bassenge",
   "adresse": "Thier Mathias 1B, 4690 Bassenge"
  },
  {
   "nom": "Oudergem (COO MENA)",
   "operateur": "coo",
   "operateurLbl": "Fedasil — COO",
   "type": "coo",
   "region": "BXL",
   "rue": "Jean Van Horenbeecklaan 192",
   "cp": "1160",
   "commune": "Oudergem",
   "adresse": "Jean Van Horenbeecklaan 192, 1160 Oudergem"
  },
  {
   "nom": "Liège Saint-Joseph",
   "operateur": "fedasil",
   "operateurLbl": "Fedasil",
   "type": "collectif",
   "region": "WAL",
   "rue": "Rue de Hesbaye 75",
   "cp": "4000",
   "commune": "Liège",
   "adresse": "Rue de Hesbaye 75, 4000 Liège"
  },
  {
   "nom": "Liège Saint-Vincent",
   "operateur": "fedasil",
   "operateurLbl": "Fedasil",
   "type": "collectif",
   "region": "WAL",
   "rue": "Rue François Lefèbvre 215",
   "cp": "4000",
   "commune": "Liège",
   "adresse": "Rue François Lefèbvre 215, 4000 Liège"
  },
  {
   "nom": "Koksijde",
   "operateur": "fedasil",
   "operateurLbl": "Fedasil",
   "type": "collectif",
   "region": "VLA",
   "rue": "Robert Vandammestraat 100A",
   "cp": "8670",
   "commune": "Koksijde",
   "adresse": "Robert Vandammestraat 100A, 8670 Koksijde"
  },
  {
   "nom": "Bredene",
   "operateur": "fedasil",
   "operateurLbl": "Fedasil",
   "type": "collectif",
   "region": "VLA",
   "rue": "Kapelstraat 88",
   "cp": "8450",
   "commune": "Bredene",
   "adresse": "Kapelstraat 88, 8450 Bredene"
  },
  {
   "nom": "Herbeumont",
   "operateur": "fedasil",
   "operateurLbl": "Fedasil",
   "type": "collectif",
   "region": "WAL",
   "rue": "Les Fourches 1",
   "cp": "6887",
   "commune": "Herbeumont",
   "adresse": "Les Fourches 1, 6887 Herbeumont"
  },
  {
   "nom": "Theux",
   "operateur": "fedasil",
   "operateurLbl": "Fedasil",
   "type": "collectif",
   "region": "WAL",
   "rue": "Route du Congrès de Polleur 53",
   "cp": "4910",
   "commune": "Theux",
   "adresse": "Route du Congrès de Polleur 53, 4910 Theux"
  },
  {
   "nom": "Gent Boot",
   "operateur": "fedasil",
   "operateurLbl": "Fedasil",
   "type": "collectif",
   "region": "VLA",
   "rue": "Rigakaai 41",
   "cp": "9000",
   "commune": "Gent",
   "adresse": "Rigakaai 41, 9000 Gent"
  },
  {
   "nom": "Zoutleeuw",
   "operateur": "fedasil",
   "operateurLbl": "Fedasil",
   "type": "collectif",
   "region": "VLA",
   "rue": "Zoutleeuwse Steenweg 11",
   "cp": "3440",
   "commune": "Zoutleeuw",
   "adresse": "Zoutleeuwse Steenweg 11, 3440 Zoutleeuw"
  },
  {
   "nom": "Senonchamps",
   "operateur": "fedasil",
   "operateurLbl": "Fedasil",
   "type": "collectif",
   "region": "WAL",
   "rue": "Senonchamps 1B",
   "cp": "6600",
   "commune": "Bastogne",
   "adresse": "Senonchamps 1B, 6600 Bastogne"
  },
  {
   "nom": "Couvin",
   "operateur": "fedasil",
   "operateurLbl": "Fedasil",
   "type": "collectif",
   "region": "WAL",
   "rue": "Rue dessus de la ville 5",
   "cp": "5660",
   "commune": "Couvin",
   "adresse": "Rue dessus de la ville 5, 5660 Couvin"
  },
  {
   "nom": "Mouscron",
   "operateur": "fedasil",
   "operateurLbl": "Fedasil",
   "type": "collectif",
   "region": "WAL",
   "rue": "Rue du Couvent 39",
   "cp": "7700",
   "commune": "Mouscron",
   "adresse": "Rue du Couvent 39, 7700 Mouscron"
  },
  {
   "nom": "Lommel",
   "operateur": "fedasil",
   "operateurLbl": "Fedasil",
   "type": "collectif",
   "region": "VLA",
   "rue": "Luikersteenweg 313A",
   "cp": "3920",
   "commune": "Lommel",
   "adresse": "Luikersteenweg 313A, 3920 Lommel"
  },
  {
   "nom": "Brussel Klein-Kasteeltje",
   "operateur": "fedasil",
   "operateurLbl": "Fedasil",
   "type": "collectif",
   "region": "BXL",
   "rue": "Negende Linielaan 27",
   "cp": "1000",
   "commune": "Brussel",
   "adresse": "Negende Linielaan 27, 1000 Brussel"
  },
  {
   "nom": "Overijse",
   "operateur": "fedasil",
   "operateurLbl": "Fedasil",
   "type": "collectif",
   "region": "VLA",
   "rue": "Homeweg 15",
   "cp": "3090",
   "commune": "Overijse",
   "adresse": "Homeweg 15, 3090 Overijse"
  },
  {
   "nom": "Hasselt",
   "operateur": "fedasil",
   "operateurLbl": "Fedasil",
   "type": "collectif",
   "region": "VLA",
   "rue": "Genkersteenweg 350",
   "cp": "3500",
   "commune": "Hasselt",
   "adresse": "Genkersteenweg 350, 3500 Hasselt"
  },
  {
   "nom": "Sint-Truiden",
   "operateur": "fedasil",
   "operateurLbl": "Fedasil",
   "type": "collectif",
   "region": "VLA",
   "rue": "Montenakenweg 145",
   "cp": "3800",
   "commune": "Sint-Truiden",
   "adresse": "Montenakenweg 145, 3800 Sint-Truiden"
  },
  {
   "nom": "Florennes",
   "operateur": "fedasil",
   "operateurLbl": "Fedasil",
   "type": "collectif",
   "region": "WAL",
   "rue": "Rue Henry de Rohan Chabot 120",
   "cp": "5620",
   "commune": "Florennes",
   "adresse": "Rue Henry de Rohan Chabot 120, 5620 Florennes"
  },
  {
   "nom": "Charleroi",
   "operateur": "fedasil",
   "operateurLbl": "Fedasil",
   "type": "collectif",
   "region": "WAL",
   "rue": "Parc Industriel 2ème rue 24",
   "cp": "6040",
   "commune": "Charleroi",
   "adresse": "Parc Industriel 2ème rue 24, 6040 Charleroi"
  },
  {
   "nom": "Sugny (COO)",
   "operateur": "coo",
   "operateurLbl": "Fedasil — COO",
   "type": "coo",
   "region": "WAL",
   "rue": "Voies de Bohan 245",
   "cp": "5550",
   "commune": "Sugny",
   "adresse": "Voies de Bohan 245, 5550 Sugny"
  },
  {
   "nom": "Arendonk",
   "operateur": "fedasil",
   "operateurLbl": "Fedasil",
   "type": "collectif",
   "region": "VLA",
   "rue": "Grens 77",
   "cp": "2370",
   "commune": "Arendonk",
   "adresse": "Grens 77, 2370 Arendonk"
  },
  {
   "nom": "Broechem",
   "operateur": "fedasil",
   "operateurLbl": "Fedasil",
   "type": "collectif",
   "region": "VLA",
   "rue": "Van den Nestlaan 104",
   "cp": "2520",
   "commune": "Broechem",
   "adresse": "Van den Nestlaan 104, 2520 Broechem"
  },
  {
   "nom": "Steenokkerzeel (COO)",
   "operateur": "coo",
   "operateurLbl": "Fedasil — COO",
   "type": "coo",
   "region": "VLA",
   "rue": "Keizerinlaan 2",
   "cp": "1820",
   "commune": "Steenokkerzeel",
   "adresse": "Keizerinlaan 2, 1820 Steenokkerzeel"
  },
  {
   "nom": "Kapellen",
   "operateur": "fedasil",
   "operateurLbl": "Fedasil",
   "type": "collectif",
   "region": "VLA",
   "rue": "Kazerneweg 35",
   "cp": "2950",
   "commune": "Kapellen",
   "adresse": "Kazerneweg 35, 2950 Kapellen"
  },
  {
   "nom": "Neder-Over-Heembeek",
   "operateur": "fedasil",
   "operateurLbl": "Fedasil",
   "type": "collectif",
   "region": "BXL",
   "rue": "Bruynstraat 11-20",
   "cp": "1120",
   "commune": "Neder-Over-Heembeek",
   "adresse": "Bruynstraat 11-20, 1120 Neder-Over-Heembeek"
  },
  {
   "nom": "Sint-Pieters-Woluwe",
   "operateur": "fedasil",
   "operateurLbl": "Fedasil",
   "type": "collectif",
   "region": "BXL",
   "rue": "Palmboomstraat 80",
   "cp": "1150",
   "commune": "Sint-Pieters-Woluwe",
   "adresse": "Palmboomstraat 80, 1150 Sint-Pieters-Woluwe"
  },
  {
   "nom": "Pondrôme",
   "operateur": "fedasil",
   "operateurLbl": "Fedasil",
   "type": "collectif",
   "region": "WAL",
   "rue": "Rue du Tombois 4",
   "cp": "5574",
   "commune": "Pondrôme",
   "adresse": "Rue du Tombois 4, 5574 Pondrôme"
  },
  {
   "nom": "Bovigny",
   "operateur": "fedasil",
   "operateurLbl": "Fedasil",
   "type": "collectif",
   "region": "WAL",
   "rue": "Chemin de Courtil 71X",
   "cp": "6671",
   "commune": "Bovigny",
   "adresse": "Chemin de Courtil 71X, 6671 Bovigny"
  },
  {
   "nom": "Rixensart",
   "operateur": "fedasil",
   "operateurLbl": "Fedasil",
   "type": "collectif",
   "region": "WAL",
   "rue": "Rue du Plagniau 1",
   "cp": "1330",
   "commune": "Rixensart",
   "adresse": "Rue du Plagniau 1, 1330 Rixensart"
  },
  {
   "nom": "Jodoigne",
   "operateur": "fedasil",
   "operateurLbl": "Fedasil",
   "type": "collectif",
   "region": "WAL",
   "rue": "Chaussée de Hannut 141",
   "cp": "1370",
   "commune": "Jodoigne",
   "adresse": "Chaussée de Hannut 141, 1370 Jodoigne"
  },
  {
   "nom": "Ixelles",
   "operateur": "croixrouge",
   "operateurLbl": "Croix-Rouge",
   "type": "collectif",
   "region": "BXL",
   "rue": "Avenue de la Couronne 42",
   "cp": "1050",
   "commune": "Ixelles",
   "adresse": "Avenue de la Couronne 42, 1050 Ixelles"
  },
  {
   "nom": "Ronse",
   "operateur": "rodekruis",
   "operateurLbl": "Rode Kruis",
   "type": "collectif",
   "region": "VLA",
   "rue": "Kruisstraat 28",
   "cp": "9600",
   "commune": "Ronse",
   "adresse": "Kruisstraat 28, 9600 Ronse"
  },
  {
   "nom": "Sint-Laureins",
   "operateur": "rodekruis",
   "operateurLbl": "Rode Kruis",
   "type": "collectif",
   "region": "VLA",
   "rue": "Leemweg 11",
   "cp": "9980",
   "commune": "Sint-Laureins",
   "adresse": "Leemweg 11, 9980 Sint-Laureins"
  },
  {
   "nom": "Ariane",
   "operateur": "rodekruis",
   "operateurLbl": "Rode Kruis",
   "type": "collectif",
   "region": "BXL",
   "rue": "Arianelaan 7",
   "cp": "1201",
   "commune": "Sint-Lambrechts-Woluwe",
   "adresse": "Arianelaan 7, 1201 Sint-Lambrechts-Woluwe"
  },
  {
   "nom": "Genappe",
   "operateur": "croixrouge",
   "operateurLbl": "Croix-Rouge",
   "type": "collectif",
   "region": "WAL",
   "rue": "Rue Couture Mathy 7",
   "cp": "1470",
   "commune": "Genappe",
   "adresse": "Rue Couture Mathy 7, 1470 Genappe"
  },
  {
   "nom": "Montegnée",
   "operateur": "croixrouge",
   "operateurLbl": "Croix-Rouge",
   "type": "collectif",
   "region": "WAL",
   "rue": "Rue Saint-Nicolas 447-449",
   "cp": "4420",
   "commune": "Montegnée",
   "adresse": "Rue Saint-Nicolas 447-449, 4420 Montegnée"
  },
  {
   "nom": "Boom",
   "operateur": "rodekruis",
   "operateurLbl": "Rode Kruis",
   "type": "collectif",
   "region": "VLA",
   "rue": "Jozef Van Cleemputplein 7",
   "cp": "2850",
   "commune": "Boom",
   "adresse": "Jozef Van Cleemputplein 7, 2850 Boom"
  },
  {
   "nom": "Verviers",
   "operateur": "croixrouge",
   "operateurLbl": "Croix-Rouge",
   "type": "collectif",
   "region": "WAL",
   "rue": "Rue aux Laines 28-30",
   "cp": "4800",
   "commune": "Verviers",
   "adresse": "Rue aux Laines 28-30, 4800 Verviers"
  },
  {
   "nom": "Evere",
   "operateur": "croixrouge",
   "operateurLbl": "Croix-Rouge",
   "type": "collectif",
   "region": "BXL",
   "rue": "Avenue Jules Bordet 74",
   "cp": "1140",
   "commune": "Evere",
   "adresse": "Avenue Jules Bordet 74, 1140 Evere"
  },
  {
   "nom": "Beveren",
   "operateur": "rodekruis",
   "operateurLbl": "Rode Kruis",
   "type": "collectif",
   "region": "VLA",
   "rue": "Stationsplein 3",
   "cp": "9120",
   "commune": "Beveren",
   "adresse": "Stationsplein 3, 9120 Beveren"
  },
  {
   "nom": "Ans-Jamar",
   "operateur": "croixrouge",
   "operateurLbl": "Croix-Rouge",
   "type": "collectif",
   "region": "WAL",
   "rue": "Rue Walthère Jamar 102b",
   "cp": "4430",
   "commune": "Ans",
   "adresse": "Rue Walthère Jamar 102b, 4430 Ans"
  },
  {
   "nom": "Wingene",
   "operateur": "rodekruis",
   "operateurLbl": "Rode Kruis",
   "type": "collectif",
   "region": "VLA",
   "rue": "Boskapeldreef 6",
   "cp": "8750",
   "commune": "Wingene",
   "adresse": "Boskapeldreef 6, 8750 Wingene"
  },
  {
   "nom": "Westakkers",
   "operateur": "rodekruis",
   "operateurLbl": "Rode Kruis",
   "type": "collectif",
   "region": "VLA",
   "rue": "Grote Baan 111",
   "cp": "9100",
   "commune": "Sint-Niklaas",
   "adresse": "Grote Baan 111, 9100 Sint-Niklaas"
  },
  {
   "nom": "Sint-Niklaas",
   "operateur": "rodekruis",
   "operateurLbl": "Rode Kruis",
   "type": "collectif",
   "region": "VLA",
   "rue": "Kasteelstraat 8",
   "cp": "9100",
   "commune": "Sint-Niklaas",
   "adresse": "Kasteelstraat 8, 9100 Sint-Niklaas"
  },
  {
   "nom": "Overpelt",
   "operateur": "rodekruis",
   "operateurLbl": "Rode Kruis",
   "type": "collectif",
   "region": "VLA",
   "rue": "Napoleonweg 51",
   "cp": "3900",
   "commune": "Overpelt",
   "adresse": "Napoleonweg 51, 3900 Overpelt"
  },
  {
   "nom": "Menen",
   "operateur": "rodekruis",
   "operateurLbl": "Rode Kruis",
   "type": "collectif",
   "region": "VLA",
   "rue": "Stationsstraat 15",
   "cp": "8930",
   "commune": "Menen",
   "adresse": "Stationsstraat 15, 8930 Menen"
  },
  {
   "nom": "Lint",
   "operateur": "rodekruis",
   "operateurLbl": "Rode Kruis",
   "type": "collectif",
   "region": "VLA",
   "rue": "Kapelstraat 1",
   "cp": "2547",
   "commune": "Lint",
   "adresse": "Kapelstraat 1, 2547 Lint"
  },
  {
   "nom": "Linkeroever",
   "operateur": "rodekruis",
   "operateurLbl": "Rode Kruis",
   "type": "collectif",
   "region": "VLA",
   "rue": "Beatrijslaan 100",
   "cp": "2050",
   "commune": "Antwerpen",
   "adresse": "Beatrijslaan 100, 2050 Antwerpen"
  },
  {
   "nom": "Leopoldsburg",
   "operateur": "rodekruis",
   "operateurLbl": "Rode Kruis",
   "type": "collectif",
   "region": "VLA",
   "rue": "Koningin Louisa-Marialaan 40",
   "cp": "3970",
   "commune": "Leopoldsburg",
   "adresse": "Koningin Louisa-Marialaan 40, 3970 Leopoldsburg"
  },
  {
   "nom": "Lanaken",
   "operateur": "rodekruis",
   "operateurLbl": "Rode Kruis",
   "type": "collectif",
   "region": "VLA",
   "rue": "Molenbergstraat 101",
   "cp": "3620",
   "commune": "Lanaken",
   "adresse": "Molenbergstraat 101, 3620 Lanaken"
  },
  {
   "nom": "Houthalen-Helchteren",
   "operateur": "rodekruis",
   "operateurLbl": "Rode Kruis",
   "type": "collectif",
   "region": "VLA",
   "rue": "Kazernelaan 125",
   "cp": "3530",
   "commune": "Houthalen-Helchteren",
   "adresse": "Kazernelaan 125, 3530 Houthalen-Helchteren"
  },
  {
   "nom": "Heusden-Zolder",
   "operateur": "rodekruis",
   "operateurLbl": "Rode Kruis",
   "type": "collectif",
   "region": "VLA",
   "rue": "Kapelstraat 73/2",
   "cp": "3550",
   "commune": "Heusden-Zolder",
   "adresse": "Kapelstraat 73/2, 3550 Heusden-Zolder"
  },
  {
   "nom": "Eeklo",
   "operateur": "rodekruis",
   "operateurLbl": "Rode Kruis",
   "type": "collectif",
   "region": "VLA",
   "rue": "Pokmoere 1A",
   "cp": "9900",
   "commune": "Eeklo",
   "adresse": "Pokmoere 1A, 9900 Eeklo"
  },
  {
   "nom": "Brugge",
   "operateur": "rodekruis",
   "operateurLbl": "Rode Kruis",
   "type": "collectif",
   "region": "VLA",
   "rue": "Vlamingstraat 55",
   "cp": "8000",
   "commune": "Brugge",
   "adresse": "Vlamingstraat 55, 8000 Brugge"
  },
  {
   "nom": "Alsemberg",
   "operateur": "rodekruis",
   "operateurLbl": "Rode Kruis",
   "type": "collectif",
   "region": "VLA",
   "rue": "Sanatoriumstraat 165",
   "cp": "1652",
   "commune": "Alsemberg",
   "adresse": "Sanatoriumstraat 165, 1652 Alsemberg"
  },
  {
   "nom": "Jambes",
   "operateur": "croixrouge",
   "operateurLbl": "Croix-Rouge",
   "type": "collectif",
   "region": "WAL",
   "rue": "Rue de Dave 270",
   "cp": "5100",
   "commune": "Jambes",
   "adresse": "Rue de Dave 270, 5100 Jambes"
  },
  {
   "nom": "Tournai",
   "operateur": "croixrouge",
   "operateurLbl": "Croix-Rouge",
   "type": "collectif",
   "region": "WAL",
   "rue": "Avenue Decraene 3",
   "cp": "7500",
   "commune": "Tournai",
   "adresse": "Avenue Decraene 3, 7500 Tournai"
  },
  {
   "nom": "Sainte-Ode",
   "operateur": "croixrouge",
   "operateurLbl": "Croix-Rouge",
   "type": "collectif",
   "region": "WAL",
   "rue": "Le Celly 2",
   "cp": "6680",
   "commune": "Sainte-Ode",
   "adresse": "Le Celly 2, 6680 Sainte-Ode"
  },
  {
   "nom": "La Jastrée",
   "operateur": "croixrouge",
   "operateurLbl": "Croix-Rouge",
   "type": "collectif",
   "region": "WAL",
   "rue": "Rue Petit-Barvaux 99",
   "cp": "6940",
   "commune": "Barvaux",
   "adresse": "Rue Petit-Barvaux 99, 6940 Barvaux"
  },
  {
   "nom": "L'Envol — CARDA",
   "operateur": "croixrouge",
   "operateurLbl": "Croix-Rouge",
   "type": "collectif",
   "region": "WAL",
   "rue": "Rue du Velroux 140",
   "cp": "4460",
   "commune": "Bierset",
   "adresse": "Rue du Velroux 140, 4460 Bierset"
  },
  {
   "nom": "Le Bocq",
   "operateur": "croixrouge",
   "operateurLbl": "Croix-Rouge",
   "type": "collectif",
   "region": "WAL",
   "rue": "Rue du Redeau 70",
   "cp": "5530",
   "commune": "Yvoir",
   "adresse": "Rue du Redeau 70, 5530 Yvoir"
  },
  {
   "nom": "Uccle",
   "operateur": "croixrouge",
   "operateurLbl": "Croix-Rouge",
   "type": "collectif",
   "region": "BXL",
   "rue": "Rue du Ham 1",
   "cp": "1180",
   "commune": "Uccle",
   "adresse": "Rue du Ham 1, 1180 Uccle"
  },
  {
   "nom": "Couleurs du monde",
   "operateur": "croixrouge",
   "operateurLbl": "Croix-Rouge",
   "type": "collectif",
   "region": "WAL",
   "rue": "Rue de Hotton 11",
   "cp": "6987",
   "commune": "Rendeux",
   "adresse": "Rue de Hotton 11, 6987 Rendeux"
  },
  {
   "nom": "Chantecler",
   "operateur": "croixrouge",
   "operateurLbl": "Croix-Rouge",
   "type": "collectif",
   "region": "WAL",
   "rue": "Rue Chantecler 27",
   "cp": "5670",
   "commune": "Oignies-en-Thiérache",
   "adresse": "Rue Chantecler 27, 5670 Oignies-en-Thiérache"
  },
  {
   "nom": "L'Amblève",
   "operateur": "croixrouge",
   "operateurLbl": "Croix-Rouge",
   "type": "collectif",
   "region": "WAL",
   "rue": "Sedoz 6",
   "cp": "4920",
   "commune": "Remouchamps",
   "adresse": "Sedoz 6, 4920 Remouchamps"
  },
  {
   "nom": "Le Relais du Monde",
   "operateur": "croixrouge",
   "operateurLbl": "Croix-Rouge",
   "type": "collectif",
   "region": "WAL",
   "rue": "Rue R. Delgrange 1",
   "cp": "5360",
   "commune": "Natoye",
   "adresse": "Rue R. Delgrange 1, 5360 Natoye"
  },
  {
   "nom": "Des Racines et des Ailes",
   "operateur": "croixrouge",
   "operateurLbl": "Croix-Rouge",
   "type": "collectif",
   "region": "WAL",
   "rue": "Route de Saint-Antoine 27",
   "cp": "6960",
   "commune": "Fays",
   "adresse": "Route de Saint-Antoine 27, 6960 Fays"
  },
  {
   "nom": "Manderfeld",
   "operateur": "croixrouge",
   "operateurLbl": "Croix-Rouge",
   "type": "collectif",
   "region": "WAL",
   "rue": "Dorf Manderfeld 350",
   "cp": "4760",
   "commune": "Bullange",
   "adresse": "Dorf Manderfeld 350, 4760 Bullange"
  },
  {
   "nom": "Jette",
   "operateur": "croixrouge",
   "operateurLbl": "Croix-Rouge",
   "type": "collectif",
   "region": "BXL",
   "rue": "Rue Fernande Volral 37",
   "cp": "1090",
   "commune": "Jette",
   "adresse": "Rue Fernande Volral 37, 1090 Jette"
  },
  {
   "nom": "Henry Dunant",
   "operateur": "croixrouge",
   "operateurLbl": "Croix-Rouge",
   "type": "collectif",
   "region": "WAL",
   "rue": "Rue de Durbuy 145",
   "cp": "6990",
   "commune": "Hotton",
   "adresse": "Rue de Durbuy 145, 6990 Hotton"
  },
  {
   "nom": "Belle-Vue Eupen",
   "operateur": "croixrouge",
   "operateurLbl": "Croix-Rouge",
   "type": "collectif",
   "region": "WAL",
   "rue": "Eichenberg 11",
   "cp": "4700",
   "commune": "Eupen",
   "adresse": "Eichenberg 11, 4700 Eupen"
  },
  {
   "nom": "La Trientale",
   "operateur": "croixrouge",
   "operateurLbl": "Croix-Rouge",
   "type": "collectif",
   "region": "WAL",
   "rue": "Rue de la Sapinière 26",
   "cp": "4141",
   "commune": "Sprimont",
   "adresse": "Rue de la Sapinière 26, 4141 Sprimont"
  },
  {
   "nom": "Rocourt",
   "operateur": "croixrouge",
   "operateurLbl": "Croix-Rouge",
   "type": "collectif",
   "region": "WAL",
   "rue": "Rue de la Tonne 80B",
   "cp": "4000",
   "commune": "Rocourt",
   "adresse": "Rue de la Tonne 80B, 4000 Rocourt"
  },
  {
   "nom": "Forest",
   "operateur": "partenaire",
   "operateurLbl": "Partenaire",
   "type": "collectif",
   "region": "BXL",
   "rue": "Avenue de Monte Carlo 178",
   "cp": "1190",
   "commune": "Forest",
   "adresse": "Avenue de Monte Carlo 178, 1190 Forest"
  },
  {
   "nom": "Amonsoli (MENA)",
   "operateur": "mena",
   "operateurLbl": "Centre MENA",
   "type": "mena",
   "region": "WAL",
   "rue": "Rue du Palais 145",
   "cp": "4800",
   "commune": "Verviers",
   "adresse": "Rue du Palais 145, 4800 Verviers"
  },
  {
   "nom": "Koekelberg",
   "operateur": "partenaire",
   "operateurLbl": "Partenaire",
   "type": "collectif",
   "region": "BXL",
   "rue": "Avenue de Jette 2",
   "cp": "1081",
   "commune": "Koekelberg",
   "adresse": "Avenue de Jette 2, 1081 Koekelberg"
  },
  {
   "nom": "Ransart",
   "operateur": "partenaire",
   "operateurLbl": "Partenaire",
   "type": "collectif",
   "region": "WAL",
   "rue": "Rue du Vigneron 59",
   "cp": "6043",
   "commune": "Ransart",
   "adresse": "Rue du Vigneron 59, 6043 Ransart"
  },
  {
   "nom": "Laeken",
   "operateur": "partenaire",
   "operateurLbl": "Partenaire",
   "type": "collectif",
   "region": "BXL",
   "rue": "Avenue de Lima 20",
   "cp": "1020",
   "commune": "Laeken",
   "adresse": "Avenue de Lima 20, 1020 Laeken"
  },
  {
   "nom": "Foyer Selah",
   "operateur": "partenaire",
   "operateurLbl": "Partenaire",
   "type": "collectif",
   "region": "BXL",
   "rue": "Ieperlaan 28",
   "cp": "1000",
   "commune": "Brussel",
   "adresse": "Ieperlaan 28, 1000 Brussel"
  },
  {
   "nom": "Scherpenheuvel",
   "operateur": "partenaire",
   "operateurLbl": "Partenaire",
   "type": "collectif",
   "region": "VLA",
   "rue": "Rozenstraat 17",
   "cp": "3270",
   "commune": "Scherpenheuvel",
   "adresse": "Rozenstraat 17, 3270 Scherpenheuvel"
  },
  {
   "nom": "Belle Vue Érezée",
   "operateur": "partenaire",
   "operateurLbl": "Partenaire",
   "type": "collectif",
   "region": "WAL",
   "rue": "Rue des Combattants 12",
   "cp": "6997",
   "commune": "Érezée",
   "adresse": "Rue des Combattants 12, 6997 Érezée"
  },
  {
   "nom": "Visages du monde",
   "operateur": "croixrouge",
   "operateurLbl": "Croix-Rouge",
   "type": "collectif",
   "region": "WAL",
   "rue": "Route de Bouillon 86",
   "cp": "6700",
   "commune": "Stockem",
   "adresse": "Route de Bouillon 86, 6700 Stockem"
  },
  {
   "nom": "Pierre Bleue",
   "operateur": "croixrouge",
   "operateurLbl": "Croix-Rouge",
   "type": "collectif",
   "region": "WAL",
   "rue": "Rue du Redeau 64",
   "cp": "5530",
   "commune": "Yvoir",
   "adresse": "Rue du Redeau 64, 5530 Yvoir"
  },
  {
   "nom": "Anderlecht",
   "operateur": "partenaire",
   "operateurLbl": "Partenaire",
   "type": "collectif",
   "region": "BXL",
   "rue": "Rue Frans Hals 90",
   "cp": "1070",
   "commune": "Anderlecht",
   "adresse": "Rue Frans Hals 90, 1070 Anderlecht"
  }
 ]
}